Workbook

Sheet README

Sheet Risk Analysis
A1: Risk Analysis — Data Entry
A2: Enter data here — the Planning View (Sheet 2) auto-sorts by Effective Priority and calculates the cut-line.
A3: Based on concepts from Systematic Software Testing by Rick Craig and Stefan Jaskiel
G4: Scoring Key: | H4: H = 5 | I4: M = 3 | J4: L = 1
A6: # | B6: Objective | C6: Inventory | D6: Likelihood | E6: L Score | F6: Impact | G6: I Score | H6: Priority | I6: Adjust (+/-) | J6: Eff. Priority | K6: Est. Hours | L6: Notes / Rationale | M6: Rank
A7: 1 | B7: Authentication | C7: Login / Logout | D7: H | E7: =IF(D7="H",5,IF(D7="M",3,IF(D7="L",1,0))) -> 5 | F7: H | G7: =IF(F7="H",5,IF(F7="M",3,IF(F7="L",1,0))) -> 5 | H7: =E7*G7 -> 25 | I7: 0 | J7: =H7+I7 -> 25 | K7: 3 | L7: Core user flow; auth provider integration | M7: =_xlfn.RANK.EQ(J7,$J$7:$J$22,0)+COUNTIFS($J$7:$J$22,J7,$A$7:$A$22,"<"&A7) -> 1
A8: 2 | B8: Authentication | C8: Password Reset | D8: M | E8: =IF(D8="H",5,IF(D8="M",3,IF(D8="L",1,0))) -> 3 | F8: M | G8: =IF(F8="H",5,IF(F8="M",3,IF(F8="L",1,0))) -> 3 | H8: =E8*G8 -> 9 | I8: 0 | J8: =H8+I8 -> 9 | K8: 2 | L8: Token-based flow; moderate complexity | M8: =_xlfn.RANK.EQ(J8,$J$7:$J$22,0)+COUNTIFS($J$7:$J$22,J8,$A$7:$A$22,"<"&A8) -> 6
A9: 3 | B9: Authentication | C9: Session Timeout | D9: L | E9: =IF(D9="H",5,IF(D9="M",3,IF(D9="L",1,0))) -> 1 | F9: M | G9: =IF(F9="H",5,IF(F9="M",3,IF(F9="L",1,0))) -> 3 | H9: =E9*G9 -> 3 | I9: 0 | J9: =H9+I9 -> 3 | K9: 1 | L9: Mature implementation; low change rate | M9: =_xlfn.RANK.EQ(J9,$J$7:$J$22,0)+COUNTIFS($J$7:$J$22,J9,$A$7:$A$22,"<"&A9) -> 9
A10: 4 | B10: Shopping Cart | C10: Add to Cart | D10: H | E10: =IF(D10="H",5,IF(D10="M",3,IF(D10="L",1,0))) -> 5 | F10: H | G10: =IF(F10="H",5,IF(F10="M",3,IF(F10="L",1,0))) -> 5 | H10: =E10*G10 -> 25 | I10: 0 | J10: =H10+I10 -> 25 | K10: 3 | L10: High traffic; frequent changes | M10: =_xlfn.RANK.EQ(J10,$J$7:$J$22,0)+COUNTIFS($J$7:$J$22,J10,$A$7:$A$22,"<"&A10) -> 2
A11: 5 | B11: Shopping Cart | C11: Update Quantity | D11: L | E11: =IF(D11="H",5,IF(D11="M",3,IF(D11="L",1,0))) -> 1 | F11: M | G11: =IF(F11="H",5,IF(F11="M",3,IF(F11="L",1,0))) -> 3 | H11: =E11*G11 -> 3 | I11: 0 | J11: =H11+I11 -> 3 | K11: 1 | L11: Simple CRUD; well-tested path | M11: =_xlfn.RANK.EQ(J11,$J$7:$J$22,0)+COUNTIFS($J$7:$J$22,J11,$A$7:$A$22,"<"&A11) -> 10
A12: 6 | B12: Shopping Cart | C12: Remove Item | D12: L | E12: =IF(D12="H",5,IF(D12="M",3,IF(D12="L",1,0))) -> 1 | F12: L | G12: =IF(F12="H",5,IF(F12="M",3,IF(F12="L",1,0))) -> 1 | H12: =E12*G12 -> 1 | I12: 0 | J12: =H12+I12 -> 1 | K12: 1 | L12: Simple operation; minimal dependencies | M12: =_xlfn.RANK.EQ(J12,$J$7:$J$22,0)+COUNTIFS($J$7:$J$22,J12,$A$7:$A$22,"<"&A12) -> 14
A13: 7 | B13: Checkout | C13: Credit Card Payment | D13: H | E13: =IF(D13="H",5,IF(D13="M",3,IF(D13="L",1,0))) -> 5 | F13: H | G13: =IF(F13="H",5,IF(F13="M",3,IF(F13="L",1,0))) -> 5 | H13: =E13*G13 -> 25 | I13: 0 | J13: =H13+I13 -> 25 | K13: 3 | L13: Payment gateway; PCI; high revenue impact | M13: =_xlfn.RANK.EQ(J13,$J$7:$J$22,0)+COUNTIFS($J$7:$J$22,J13,$A$7:$A$22,"<"&A13) -> 3
A14: 8 | B14: Checkout | C14: Guest Checkout | D14: H | E14: =IF(D14="H",5,IF(D14="M",3,IF(D14="L",1,0))) -> 5 | F14: H | G14: =IF(F14="H",5,IF(F14="M",3,IF(F14="L",1,0))) -> 5 | H14: =E14*G14 -> 25 | I14: 0 | J14: =H14+I14 -> 25 | K14: 2.5 | L14: Alternative path; less tested | M14: =_xlfn.RANK.EQ(J14,$J$7:$J$22,0)+COUNTIFS($J$7:$J$22,J14,$A$7:$A$22,"<"&A14) -> 4
A15: 9 | B15: Checkout | C15: Coupon Codes | D15: M | E15: =IF(D15="H",5,IF(D15="M",3,IF(D15="L",1,0))) -> 3 | F15: L | G15: =IF(F15="H",5,IF(F15="M",3,IF(F15="L",1,0))) -> 1 | H15: =E15*G15 -> 3 | I15: 0 | J15: =H15+I15 -> 3 | K15: 2 | L15: Business logic complexity; low impact | M15: =_xlfn.RANK.EQ(J15,$J$7:$J$22,0)+COUNTIFS($J$7:$J$22,J15,$A$7:$A$22,"<"&A15) -> 11
A16: 10 | B16: Checkout | C16: Tax Calculation | D16: L | E16: =IF(D16="H",5,IF(D16="M",3,IF(D16="L",1,0))) -> 1 | F16: H | G16: =IF(F16="H",5,IF(F16="M",3,IF(F16="L",1,0))) -> 5 | H16: =E16*G16 -> 5 | I16: 0 | J16: =H16+I16 -> 5 | K16: 2 | L16: Mature engine; regulatory implications | M16: =_xlfn.RANK.EQ(J16,$J$7:$J$22,0)+COUNTIFS($J$7:$J$22,J16,$A$7:$A$22,"<"&A16) -> 8
A17: 11 | B17: Notifications | C17: Order Confirmation Email | D17: M | E17: =IF(D17="H",5,IF(D17="M",3,IF(D17="L",1,0))) -> 3 | F17: M | G17: =IF(F17="H",5,IF(F17="M",3,IF(F17="L",1,0))) -> 3 | H17: =E17*G17 -> 9 | I17: 0 | J17: =H17+I17 -> 9 | K17: 1 | L17: Email service; template rendering | M17: =_xlfn.RANK.EQ(J17,$J$7:$J$22,0)+COUNTIFS($J$7:$J$22,J17,$A$7:$A$22,"<"&A17) -> 7
A18: 12 | B18: Notifications | C18: Shipping Notifications | D18: L | E18: =IF(D18="H",5,IF(D18="M",3,IF(D18="L",1,0))) -> 1 | F18: L | G18: =IF(F18="H",5,IF(F18="M",3,IF(F18="L",1,0))) -> 1 | H18: =E18*G18 -> 1 | I18: 0 | J18: =H18+I18 -> 1 | K18: 1 | L18: Third-party API; informational only | M18: =_xlfn.RANK.EQ(J18,$J$7:$J$22,0)+COUNTIFS($J$7:$J$22,J18,$A$7:$A$22,"<"&A18) -> 15
... A22: 16 | B22: Reporting | C22: Inventory Reports | D22: L | E22: =IF(D22="H",5,IF(D22="M",3,IF(D22="L",1,0))) -> 1 | F22: M | G22: =IF(F22="H",5,IF(F22="M",3,IF(F22="L",1,0))) -> 3 | H22: =E22*G22 -> 3 | I22: 0 | J22: =H22+I22 -> 3 | K22: 1 | L22: Backend reporting; operational visibility | M22: =_xlfn.RANK.EQ(J22,$J$7:$J$22,0)+COUNTIFS($J$7:$J$22,J22,$A$7:$A$22,"<"&A22) -> 13
J23: Total: | K23: =SUM(K7:K22) -> 26.5 | L23: hours (estimated execution time)
A25: Enter H/M/L in Likelihood and Impact. Adjust (+/-) lets you manually bump priority for individual items — use it to break ties or override the computed ranking. The Planning View sorts by Effective Priority.

Sheet Planning View
A1: Planning View — Sorted by Effective Priority
A3: Inputs: | C3: # Testers: | D3: 1 | E3: Hrs/Tester/Day: | F3: 5 | G3: Start Date: | H3: 46174 | I3: End Date: | J3: 46178
A4: Capacity: | B4: =NETWORKDAYS(H3,J3) -> 5 | C4: business days | D4: =D3*F3*B4 -> 25 | E4: hours available | G4: Coverage: | H4: =COUNTIF(K7:K22,"Test this cycle") -> 14 | I4: ="of "&COUNTA(C7:C22)&" items" -> of 16 items
A6: # | B6: Objective | C6: Inventory | D6: Likelihood | E6: Impact | F6: Priority | G6: Adjust | H6: Eff. Priority | I6: Est. Hours | J6: Cum. Hours | K6: Status
A7: 1 | B7: =IFERROR(INDEX('Risk Analysis'!$B$7:$B$22,MATCH(1,'Risk Analysis'!$M$7:$M$22,0)),"") -> Authentication | C7: =IFERROR(INDEX('Risk Analysis'!$C$7:$C$22,MATCH(1,'Risk Analysis'!$M$7:$M$22,0)),"") -> Login / Logout | D7: =IFERROR(INDEX('Risk Analysis'!$D$7:$D$22,MATCH(1,'Risk Analysis'!$M$7:$M$22,0)),"") -> H | E7: =IFERROR(INDEX('Risk Analysis'!$F$7:$F$22,MATCH(1,'Risk Analysis'!$M$7:$M$22,0)),"") -> H | F7: =IFERROR(INDEX('Risk Analysis'!$H$7:$H$22,MATCH(1,'Risk Analysis'!$M$7:$M$22,0)),"") -> 25 | G7: =IFERROR(INDEX('Risk Analysis'!$I$7:$I$22,MATCH(1,'Risk Analysis'!$M$7:$M$22,0)),"") -> 0 | H7: =IFERROR(INDEX('Risk Analysis'!$J$7:$J$22,MATCH(1,'Risk Analysis'!$M$7:$M$22,0)),"") -> 25 | I7: =IFERROR(INDEX('Risk Analysis'!$K$7:$K$22,MATCH(1,'Risk Analysis'!$M$7:$M$22,0)),"") -> 3 | J7: =IF(I7="","",I7) -> 3 | K7: =IF(I7="","",IF(J7<=$D$4,"Test this cycle","Deferred")) -> Test this cycle
A8: 2 | B8: =IFERROR(INDEX('Risk Analysis'!$B$7:$B$22,MATCH(2,'Risk Analysis'!$M$7:$M$22,0)),"") -> Shopping Cart | C8: =IFERROR(INDEX('Risk Analysis'!$C$7:$C$22,MATCH(2,'Risk Analysis'!$M$7:$M$22,0)),"") -> Add to Cart | D8: =IFERROR(INDEX('Risk Analysis'!$D$7:$D$22,MATCH(2,'Risk Analysis'!$M$7:$M$22,0)),"") -> H | E8: =IFERROR(INDEX('Risk Analysis'!$F$7:$F$22,MATCH(2,'Risk Analysis'!$M$7:$M$22,0)),"") -> H | F8: =IFERROR(INDEX('Risk Analysis'!$H$7:$H$22,MATCH(2,'Risk Analysis'!$M$7:$M$22,0)),"") -> 25 | G8: =IFERROR(INDEX('Risk Analysis'!$I$7:$I$22,MATCH(2,'Risk Analysis'!$M$7:$M$22,0)),"") -> 0 | H8: =IFERROR(INDEX('Risk Analysis'!$J$7:$J$22,MATCH(2,'Risk Analysis'!$M$7:$M$22,0)),"") -> 25 | I8: =IFERROR(INDEX('Risk Analysis'!$K$7:$K$22,MATCH(2,'Risk Analysis'!$M$7:$M$22,0)),"") -> 3 | J8: =IF(I8="","",J7+I8) -> 6 | K8: =IF(I8="","",IF(J8<=$D$4,"Test this cycle",IF(J7<=$D$4,"At capacity","Deferred"))) -> Test this cycle
A9: 3 | B9: =IFERROR(INDEX('Risk Analysis'!$B$7:$B$22,MATCH(3,'Risk Analysis'!$M$7:$M$22,0)),"") -> Checkout | C9: =IFERROR(INDEX('Risk Analysis'!$C$7:$C$22,MATCH(3,'Risk Analysis'!$M$7:$M$22,0)),"") -> Credit Card Payment | D9: =IFERROR(INDEX('Risk Analysis'!$D$7:$D$22,MATCH(3,'Risk Analysis'!$M$7:$M$22,0)),"") -> H | E9: =IFERROR(INDEX('Risk Analysis'!$F$7:$F$22,MATCH(3,'Risk Analysis'!$M$7:$M$22,0)),"") -> H | F9: =IFERROR(INDEX('Risk Analysis'!$H$7:$H$22,MATCH(3,'Risk Analysis'!$M$7:$M$22,0)),"") -> 25 | G9: =IFERROR(INDEX('Risk Analysis'!$I$7:$I$22,MATCH(3,'Risk Analysis'!$M$7:$M$22,0)),"") -> 0 | H9: =IFERROR(INDEX('Risk Analysis'!$J$7:$J$22,MATCH(3,'Risk Analysis'!$M$7:$M$22,0)),"") -> 25 | I9: =IFERROR(INDEX('Risk Analysis'!$K$7:$K$22,MATCH(3,'Risk Analysis'!$M$7:$M$22,0)),"") -> 3 | J9: =IF(I9="","",J8+I9) -> 9 | K9: =IF(I9="","",IF(J9<=$D$4,"Test this cycle",IF(J8<=$D$4,"At capacity","Deferred"))) -> Test this cycle
A10: 4 | B10: =IFERROR(INDEX('Risk Analysis'!$B$7:$B$22,MATCH(4,'Risk Analysis'!$M$7:$M$22,0)),"") -> Checkout | C10: =IFERROR(INDEX('Risk Analysis'!$C$7:$C$22,MATCH(4,'Risk Analysis'!$M$7:$M$22,0)),"") -> Guest Checkout | D10: =IFERROR(INDEX('Risk Analysis'!$D$7:$D$22,MATCH(4,'Risk Analysis'!$M$7:$M$22,0)),"") -> H | E10: =IFERROR(INDEX('Risk Analysis'!$F$7:$F$22,MATCH(4,'Risk Analysis'!$M$7:$M$22,0)),"") -> H | F10: =IFERROR(INDEX('Risk Analysis'!$H$7:$H$22,MATCH(4,'Risk Analysis'!$M$7:$M$22,0)),"") -> 25 | G10: =IFERROR(INDEX('Risk Analysis'!$I$7:$I$22,MATCH(4,'Risk Analysis'!$M$7:$M$22,0)),"") -> 0 | H10: =IFERROR(INDEX('Risk Analysis'!$J$7:$J$22,MATCH(4,'Risk Analysis'!$M$7:$M$22,0)),"") -> 25 | I10: =IFERROR(INDEX('Risk Analysis'!$K$7:$K$22,MATCH(4,'Risk Analysis'!$M$7:$M$22,0)),"") -> 2.5 | J10: =IF(I10="","",J9+I10) -> 11.5 | K10: =IF(I10="","",IF(J10<=$D$4,"Test this cycle",IF(J9<=$D$4,"At capacity","Deferred"))) -> Test this cycle
A11: 5 | B11: =IFERROR(INDEX('Risk Analysis'!$B$7:$B$22,MATCH(5,'Risk Analysis'!$M$7:$M$22,0)),"") -> User Admin | C11: =IFERROR(INDEX('Risk Analysis'!$C$7:$C$22,MATCH(5,'Risk Analysis'!$M$7:$M$22,0)),"") -> User Registration | D11: =IFERROR(INDEX('Risk Analysis'!$D$7:$D$22,MATCH(5,'Risk Analysis'!$M$7:$M$22,0)),"") -> M | E11: =IFERROR(INDEX('Risk Analysis'!$F$7:$F$22,MATCH(5,'Risk Analysis'!$M$7:$M$22,0)),"") -> H | F11: =IFERROR(INDEX('Risk Analysis'!$H$7:$H$22,MATCH(5,'Risk Analysis'!$M$7:$M$22,0)),"") -> 15 | G11: =IFERROR(INDEX('Risk Analysis'!$I$7:$I$22,MATCH(5,'Risk Analysis'!$M$7:$M$22,0)),"") -> 0 | H11: =IFERROR(INDEX('Risk Analysis'!$J$7:$J$22,MATCH(5,'Risk Analysis'!$M$7:$M$22,0)),"") -> 15 | I11: =IFERROR(INDEX('Risk Analysis'!$K$7:$K$22,MATCH(5,'Risk Analysis'!$M$7:$M$22,0)),"") -> 1.5 | J11: =IF(I11="","",J10+I11) -> 13 | K11: =IF(I11="","",IF(J11<=$D$4,"Test this cycle",IF(J10<=$D$4,"At capacity","Deferred"))) -> Test this cycle
A12: 6 | B12: =IFERROR(INDEX('Risk Analysis'!$B$7:$B$22,MATCH(6,'Risk Analysis'!$M$7:$M$22,0)),"") -> Authentication | C12: =IFERROR(INDEX('Risk Analysis'!$C$7:$C$22,MATCH(6,'Risk Analysis'!$M$7:$M$22,0)),"") -> Password Reset | D12: =IFERROR(INDEX('Risk Analysis'!$D$7:$D$22,MATCH(6,'Risk Analysis'!$M$7:$M$22,0)),"") -> M | E12: =IFERROR(INDEX('Risk Analysis'!$F$7:$F$22,MATCH(6,'Risk Analysis'!$M$7:$M$22,0)),"") -> M | F12: =IFERROR(INDEX('Risk Analysis'!$H$7:$H$22,MATCH(6,'Risk Analysis'!$M$7:$M$22,0)),"") -> 9 | G12: =IFERROR(INDEX('Risk Analysis'!$I$7:$I$22,MATCH(6,'Risk Analysis'!$M$7:$M$22,0)),"") -> 0 | H12: =IFERROR(INDEX('Risk Analysis'!$J$7:$J$22,MATCH(6,'Risk Analysis'!$M$7:$M$22,0)),"") -> 9 | I12: =IFERROR(INDEX('Risk Analysis'!$K$7:$K$22,MATCH(6,'Risk Analysis'!$M$7:$M$22,0)),"") -> 2 | J12: =IF(I12="","",J11+I12) -> 15 | K12: =IF(I12="","",IF(J12<=$D$4,"Test this cycle",IF(J11<=$D$4,"At capacity","Deferred"))) -> Test this cycle
A13: 7 | B13: =IFERROR(INDEX('Risk Analysis'!$B$7:$B$22,MATCH(7,'Risk Analysis'!$M$7:$M$22,0)),"") -> Notifications | C13: =IFERROR(INDEX('Risk Analysis'!$C$7:$C$22,MATCH(7,'Risk Analysis'!$M$7:$M$22,0)),"") -> Order Confirmation Email | D13: =IFERROR(INDEX('Risk Analysis'!$D$7:$D$22,MATCH(7,'Risk Analysis'!$M$7:$M$22,0)),"") -> M | E13: =IFERROR(INDEX('Risk Analysis'!$F$7:$F$22,MATCH(7,'Risk Analysis'!$M$7:$M$22,0)),"") -> M | F13: =IFERROR(INDEX('Risk Analysis'!$H$7:$H$22,MATCH(7,'Risk Analysis'!$M$7:$M$22,0)),"") -> 9 | G13: =IFERROR(INDEX('Risk Analysis'!$I$7:$I$22,MATCH(7,'Risk Analysis'!$M$7:$M$22,0)),"") -> 0 | H13: =IFERROR(INDEX('Risk Analysis'!$J$7:$J$22,MATCH(7,'Risk Analysis'!$M$7:$M$22,0)),"") -> 9 | I13: =IFERROR(INDEX('Risk Analysis'!$K$7:$K$22,MATCH(7,'Risk Analysis'!$M$7:$M$22,0)),"") -> 1 | J13: =IF(I13="","",J12+I13) -> 16 | K13: =IF(I13="","",IF(J13<=$D$4,"Test this cycle",IF(J12<=$D$4,"At capacity","Deferred"))) -> Test this cycle
A14: 8 | B14: =IFERROR(INDEX('Risk Analysis'!$B$7:$B$22,MATCH(8,'Risk Analysis'!$M$7:$M$22,0)),"") -> Checkout | C14: =IFERROR(INDEX('Risk Analysis'!$C$7:$C$22,MATCH(8,'Risk Analysis'!$M$7:$M$22,0)),"") -> Tax Calculation | D14: =IFERROR(INDEX('Risk Analysis'!$D$7:$D$22,MATCH(8,'Risk Analysis'!$M$7:$M$22,0)),"") -> L | E14: =IFERROR(INDEX('Risk Analysis'!$F$7:$F$22,MATCH(8,'Risk Analysis'!$M$7:$M$22,0)),"") -> H | F14: =IFERROR(INDEX('Risk Analysis'!$H$7:$H$22,MATCH(8,'Risk Analysis'!$M$7:$M$22,0)),"") -> 5 | G14: =IFERROR(INDEX('Risk Analysis'!$I$7:$I$22,MATCH(8,'Risk Analysis'!$M$7:$M$22,0)),"") -> 0 | H14: =IFERROR(INDEX('Risk Analysis'!$J$7:$J$22,MATCH(8,'Risk Analysis'!$M$7:$M$22,0)),"") -> 5 | I14: =IFERROR(INDEX('Risk Analysis'!$K$7:$K$22,MATCH(8,'Risk Analysis'!$M$7:$M$22,0)),"") -> 2 | J14: =IF(I14="","",J13+I14) -> 18 | K14: =IF(I14="","",IF(J14<=$D$4,"Test this cycle",IF(J13<=$D$4,"At capacity","Deferred"))) -> Test this cycle
A15: 9 | B15: =IFERROR(INDEX('Risk Analysis'!$B$7:$B$22,MATCH(9,'Risk Analysis'!$M$7:$M$22,0)),"") -> Authentication | C15: =IFERROR(INDEX('Risk Analysis'!$C$7:$C$22,MATCH(9,'Risk Analysis'!$M$7:$M$22,0)),"") -> Session Timeout | D15: =IFERROR(INDEX('Risk Analysis'!$D$7:$D$22,MATCH(9,'Risk Analysis'!$M$7:$M$22,0)),"") -> L | E15: =IFERROR(INDEX('Risk Analysis'!$F$7:$F$22,MATCH(9,'Risk Analysis'!$M$7:$M$22,0)),"") -> M | F15: =IFERROR(INDEX('Risk Analysis'!$H$7:$H$22,MATCH(9,'Risk Analysis'!$M$7:$M$22,0)),"") -> 3 | G15: =IFERROR(INDEX('Risk Analysis'!$I$7:$I$22,MATCH(9,'Risk Analysis'!$M$7:$M$22,0)),"") -> 0 | H15: =IFERROR(INDEX('Risk Analysis'!$J$7:$J$22,MATCH(9,'Risk Analysis'!$M$7:$M$22,0)),"") -> 3 | I15: =IFERROR(INDEX('Risk Analysis'!$K$7:$K$22,MATCH(9,'Risk Analysis'!$M$7:$M$22,0)),"") -> 1 | J15: =IF(I15="","",J14+I15) -> 19 | K15: =IF(I15="","",IF(J15<=$D$4,"Test this cycle",IF(J14<=$D$4,"At capacity","Deferred"))) -> Test this cycle
A16: 10 | B16: =IFERROR(INDEX('Risk Analysis'!$B$7:$B$22,MATCH(10,'Risk Analysis'!$M$7:$M$22,0)),"") -> Shopping Cart | C16: =IFERROR(INDEX('Risk Analysis'!$C$7:$C$22,MATCH(10,'Risk Analysis'!$M$7:$M$22,0)),"") -> Update Quantity | D16: =IFERROR(INDEX('Risk Analysis'!$D$7:$D$22,MATCH(10,'Risk Analysis'!$M$7:$M$22,0)),"") -> L | E16: =IFERROR(INDEX('Risk Analysis'!$F$7:$F$22,MATCH(10,'Risk Analysis'!$M$7:$M$22,0)),"") -> M | F16: =IFERROR(INDEX('Risk Analysis'!$H$7:$H$22,MATCH(10,'Risk Analysis'!$M$7:$M$22,0)),"") -> 3 | G16: =IFERROR(INDEX('Risk Analysis'!$I$7:$I$22,MATCH(10,'Risk Analysis'!$M$7:$M$22,0)),"") -> 0 | H16: =IFERROR(INDEX('Risk Analysis'!$J$7:$J$22,MATCH(10,'Risk Analysis'!$M$7:$M$22,0)),"") -> 3 | I16: =IFERROR(INDEX('Risk Analysis'!$K$7:$K$22,MATCH(10,'Risk Analysis'!$M$7:$M$22,0)),"") -> 1 | J16: =IF(I16="","",J15+I16) -> 20 | K16: =IF(I16="","",IF(J16<=$D$4,"Test this cycle",IF(J15<=$D$4,"At capacity","Deferred"))) -> Test this cycle
A17: 11 | B17: =IFERROR(INDEX('Risk Analysis'!$B$7:$B$22,MATCH(11,'Risk Analysis'!$M$7:$M$22,0)),"") -> Checkout | C17: =IFERROR(INDEX('Risk Analysis'!$C$7:$C$22,MATCH(11,'Risk Analysis'!$M$7:$M$22,0)),"") -> Coupon Codes | D17: =IFERROR(INDEX('Risk Analysis'!$D$7:$D$22,MATCH(11,'Risk Analysis'!$M$7:$M$22,0)),"") -> M | E17: =IFERROR(INDEX('Risk Analysis'!$F$7:$F$22,MATCH(11,'Risk Analysis'!$M$7:$M$22,0)),"") -> L | F17: =IFERROR(INDEX('Risk Analysis'!$H$7:$H$22,MATCH(11,'Risk Analysis'!$M$7:$M$22,0)),"") -> 3 | G17: =IFERROR(INDEX('Risk Analysis'!$I$7:$I$22,MATCH(11,'Risk Analysis'!$M$7:$M$22,0)),"") -> 0 | H17: =IFERROR(INDEX('Risk Analysis'!$J$7:$J$22,MATCH(11,'Risk Analysis'!$M$7:$M$22,0)),"") -> 3 | I17: =IFERROR(INDEX('Risk Analysis'!$K$7:$K$22,MATCH(11,'Risk Analysis'!$M$7:$M$22,0)),"") -> 2 | J17: =IF(I17="","",J16+I17) -> 22 | K17: =IF(I17="","",IF(J17<=$D$4,"Test this cycle",IF(J16<=$D$4,"At capacity","Deferred"))) -> Test this cycle
A18: 12 | B18: =IFERROR(INDEX('Risk Analysis'!$B$7:$B$22,MATCH(12,'Risk Analysis'!$M$7:$M$22,0)),"") -> Reporting | C18: =IFERROR(INDEX('Risk Analysis'!$C$7:$C$22,MATCH(12,'Risk Analysis'!$M$7:$M$22,0)),"") -> Sales Reports | D18: =IFERROR(INDEX('Risk Analysis'!$D$7:$D$22,MATCH(12,'Risk Analysis'!$M$7:$M$22,0)),"") -> L | E18: =IFERROR(INDEX('Risk Analysis'!$F$7:$F$22,MATCH(12,'Risk Analysis'!$M$7:$M$22,0)),"") -> M | F18: =IFERROR(INDEX('Risk Analysis'!$H$7:$H$22,MATCH(12,'Risk Analysis'!$M$7:$M$22,0)),"") -> 3 | G18: =IFERROR(INDEX('Risk Analysis'!$I$7:$I$22,MATCH(12,'Risk Analysis'!$M$7:$M$22,0)),"") -> 0 | H18: =IFERROR(INDEX('Risk Analysis'!$J$7:$J$22,MATCH(12,'Risk Analysis'!$M$7:$M$22,0)),"") -> 3 | I18: =IFERROR(INDEX('Risk Analysis'!$K$7:$K$22,MATCH(12,'Risk Analysis'!$M$7:$M$22,0)),"") -> 1 | J18: =IF(I18="","",J17+I18) -> 23 | K18: =IF(I18="","",IF(J18<=$D$4,"Test this cycle",IF(J17<=$D$4,"At capacity","Deferred"))) -> Test this cycle
A19: 13 | B19: =IFERROR(INDEX('Risk Analysis'!$B$7:$B$22,MATCH(13,'Risk Analysis'!$M$7:$M$22,0)),"") -> Reporting | C19: =IFERROR(INDEX('Risk Analysis'!$C$7:$C$22,MATCH(13,'Risk Analysis'!$M$7:$M$22,0)),"") -> Inventory Reports | D19: =IFERROR(INDEX('Risk Analysis'!$D$7:$D$22,MATCH(13,'Risk Analysis'!$M$7:$M$22,0)),"") -> L | E19: =IFERROR(INDEX('Risk Analysis'!$F$7:$F$22,MATCH(13,'Risk Analysis'!$M$7:$M$22,0)),"") -> M | F19: =IFERROR(INDEX('Risk Analysis'!$H$7:$H$22,MATCH(13,'Risk Analysis'!$M$7:$M$22,0)),"") -> 3 | G19: =IFERROR(INDEX('Risk Analysis'!$I$7:$I$22,MATCH(13,'Risk Analysis'!$M$7:$M$22,0)),"") -> 0 | H19: =IFERROR(INDEX('Risk Analysis'!$J$7:$J$22,MATCH(13,'Risk Analysis'!$M$7:$M$22,0)),"") -> 3 | I19: =IFERROR(INDEX('Risk Analysis'!$K$7:$K$22,MATCH(13,'Risk Analysis'!$M$7:$M$22,0)),"") -> 1 | J19: =IF(I19="","",J18+I19) -> 24 | K19: =IF(I19="","",IF(J19<=$D$4,"Test this cycle",IF(J18<=$D$4,"At capacity","Deferred"))) -> Test this cycle
A20: 14 | B20: =IFERROR(INDEX('Risk Analysis'!$B$7:$B$22,MATCH(14,'Risk Analysis'!$M$7:$M$22,0)),"") -> Shopping Cart | C20: =IFERROR(INDEX('Risk Analysis'!$C$7:$C$22,MATCH(14,'Risk Analysis'!$M$7:$M$22,0)),"") -> Remove Item | D20: =IFERROR(INDEX('Risk Analysis'!$D$7:$D$22,MATCH(14,'Risk Analysis'!$M$7:$M$22,0)),"") -> L | E20: =IFERROR(INDEX('Risk Analysis'!$F$7:$F$22,MATCH(14,'Risk Analysis'!$M$7:$M$22,0)),"") -> L | F20: =IFERROR(INDEX('Risk Analysis'!$H$7:$H$22,MATCH(14,'Risk Analysis'!$M$7:$M$22,0)),"") -> 1 | G20: =IFERROR(INDEX('Risk Analysis'!$I$7:$I$22,MATCH(14,'Risk Analysis'!$M$7:$M$22,0)),"") -> 0 | H20: =IFERROR(INDEX('Risk Analysis'!$J$7:$J$22,MATCH(14,'Risk Analysis'!$M$7:$M$22,0)),"") -> 1 | I20: =IFERROR(INDEX('Risk Analysis'!$K$7:$K$22,MATCH(14,'Risk Analysis'!$M$7:$M$22,0)),"") -> 1 | J20: =IF(I20="","",J19+I20) -> 25 | K20: =IF(I20="","",IF(J20<=$D$4,"Test this cycle",IF(J19<=$D$4,"At capacity","Deferred"))) -> Test this cycle
A21: 15 | B21: =IFERROR(INDEX('Risk Analysis'!$B$7:$B$22,MATCH(15,'Risk Analysis'!$M$7:$M$22,0)),"") -> Notifications | C21: =IFERROR(INDEX('Risk Analysis'!$C$7:$C$22,MATCH(15,'Risk Analysis'!$M$7:$M$22,0)),"") -> Shipping Notifications | D21: =IFERROR(INDEX('Risk Analysis'!$D$7:$D$22,MATCH(15,'Risk Analysis'!$M$7:$M$22,0)),"") -> L | E21: =IFERROR(INDEX('Risk Analysis'!$F$7:$F$22,MATCH(15,'Risk Analysis'!$M$7:$M$22,0)),"") -> L | F21: =IFERROR(INDEX('Risk Analysis'!$H$7:$H$22,MATCH(15,'Risk Analysis'!$M$7:$M$22,0)),"") -> 1 | G21: =IFERROR(INDEX('Risk Analysis'!$I$7:$I$22,MATCH(15,'Risk Analysis'!$M$7:$M$22,0)),"") -> 0 | H21: =IFERROR(INDEX('Risk Analysis'!$J$7:$J$22,MATCH(15,'Risk Analysis'!$M$7:$M$22,0)),"") -> 1 | I21: =IFERROR(INDEX('Risk Analysis'!$K$7:$K$22,MATCH(15,'Risk Analysis'!$M$7:$M$22,0)),"") -> 1 | J21: =IF(I21="","",J20+I21) -> 26 | K21: =IF(I21="","",IF(J21<=$D$4,"Test this cycle",IF(J20<=$D$4,"At capacity","Deferred"))) -> At capacity
A22: 16 | B22: =IFERROR(INDEX('Risk Analysis'!$B$7:$B$22,MATCH(16,'Risk Analysis'!$M$7:$M$22,0)),"") -> User Admin | C22: =IFERROR(INDEX('Risk Analysis'!$C$7:$C$22,MATCH(16,'Risk Analysis'!$M$7:$M$22,0)),"") -> Profile Management | D22: =IFERROR(INDEX('Risk Analysis'!$D$7:$D$22,MATCH(16,'Risk Analysis'!$M$7:$M$22,0)),"") -> L | E22: =IFERROR(INDEX('Risk Analysis'!$F$7:$F$22,MATCH(16,'Risk Analysis'!$M$7:$M$22,0)),"") -> L | F22: =IFERROR(INDEX('Risk Analysis'!$H$7:$H$22,MATCH(16,'Risk Analysis'!$M$7:$M$22,0)),"") -> 1 | G22: =IFERROR(INDEX('Risk Analysis'!$I$7:$I$22,MATCH(16,'Risk Analysis'!$M$7:$M$22,0)),"") -> 0 | H22: =IFERROR(INDEX('Risk Analysis'!$J$7:$J$22,MATCH(16,'Risk Analysis'!$M$7:$M$22,0)),"") -> 1 | I22: =IFERROR(INDEX('Risk Analysis'!$K$7:$K$22,MATCH(16,'Risk Analysis'!$M$7:$M$22,0)),"") -> 0.5 | J22: =IF(I22="","",J21+I22) -> 26.5 | K22: =IF(I22="","",IF(J22<=$D$4,"Test this cycle",IF(J21<=$D$4,"At capacity","Deferred"))) -> Deferred
H23: Total: | I23: =SUM(I7:I22) -> 26.5 | J23: total hours | K23: Above cut-line:
A24: ="Above cut-line: "&TEXT(SUMIF(K7:K22,"Test this cycle",I7:I22),"0.0")&" hours of "&TEXT(D4,"0.0")&" available | Adjust planning inputs (amber cells) or Adjust (+/-) values on Risk Analysis sheet to change the cut-line." -> Above cut-line: 25.0 hours of 25.0 available | Adjust planning inputs (amber cells) or Adjust (+/-) values on Risk Analysis sheet to change the cut-line.

Sheet Template
A1: Risk Analysis Template
A2: Copy this sheet for new projects. Enter objectives, inventories, and H/M/L ratings.
G3: Scoring Key: | H3: H = 5 | I3: M = 3 | J3: L = 1
A5: # | B5: Objective | C5: Inventory | D5: Likelihood | E5: L Score | F5: Impact | G5: I Score | H5: Priority | I5: Adjust (+/-) | J5: Eff. Priority | K5: Est. Hours | L5: Notes / Rationale
A6: 1 | E6: =IF(D6="H",5,IF(D6="M",3,IF(D6="L",1,""))) | G6: =IF(F6="H",5,IF(F6="M",3,IF(F6="L",1,""))) | H6: =IF(AND(E6<>"",G6<>""),E6*G6,"") | I6: 0 | J6: =IF(H6="","",H6+I6)
A7: 2 | E7: =IF(D7="H",5,IF(D7="M",3,IF(D7="L",1,""))) | G7: =IF(F7="H",5,IF(F7="M",3,IF(F7="L",1,""))) | H7: =IF(AND(E7<>"",G7<>""),E7*G7,"") | I7: 0 | J7: =IF(H7="","",H7+I7)
A8: 3 | E8: =IF(D8="H",5,IF(D8="M",3,IF(D8="L",1,""))) | G8: =IF(F8="H",5,IF(F8="M",3,IF(F8="L",1,""))) | H8: =IF(AND(E8<>"",G8<>""),E8*G8,"") | I8: 0 | J8: =IF(H8="","",H8+I8)
A9: 4 | E9: =IF(D9="H",5,IF(D9="M",3,IF(D9="L",1,""))) | G9: =IF(F9="H",5,IF(F9="M",3,IF(F9="L",1,""))) | H9: =IF(AND(E9<>"",G9<>""),E9*G9,"") | I9: 0 | J9: =IF(H9="","",H9+I9)
A10: 5 | E10: =IF(D10="H",5,IF(D10="M",3,IF(D10="L",1,""))) | G10: =IF(F10="H",5,IF(F10="M",3,IF(F10="L",1,""))) | H10: =IF(AND(E10<>"",G10<>""),E10*G10,"") | I10: 0 | J10: =IF(H10="","",H10+I10)
A11: 6 | E11: =IF(D11="H",5,IF(D11="M",3,IF(D11="L",1,""))) | G11: =IF(F11="H",5,IF(F11="M",3,IF(F11="L",1,""))) | H11: =IF(AND(E11<>"",G11<>""),E11*G11,"") | I11: 0 | J11: =IF(H11="","",H11+I11)
A12: 7 | E12: =IF(D12="H",5,IF(D12="M",3,IF(D12="L",1,""))) | G12: =IF(F12="H",5,IF(F12="M",3,IF(F12="L",1,""))) | H12: =IF(AND(E12<>"",G12<>""),E12*G12,"") | I12: 0 | J12: =IF(H12="","",H12+I12)
A13: 8 | E13: =IF(D13="H",5,IF(D13="M",3,IF(D13="L",1,""))) | G13: =IF(F13="H",5,IF(F13="M",3,IF(F13="L",1,""))) | H13: =IF(AND(E13<>"",G13<>""),E13*G13,"") | I13: 0 | J13: =IF(H13="","",H13+I13)
A14: 9 | E14: =IF(D14="H",5,IF(D14="M",3,IF(D14="L",1,""))) | G14: =IF(F14="H",5,IF(F14="M",3,IF(F14="L",1,""))) | H14: =IF(AND(E14<>"",G14<>""),E14*G14,"") | I14: 0 | J14: =IF(H14="","",H14+I14)
A15: 10 | E15: =IF(D15="H",5,IF(D15="M",3,IF(D15="L",1,""))) | G15: =IF(F15="H",5,IF(F15="M",3,IF(F15="L",1,""))) | H15: =IF(AND(E15<>"",G15<>""),E15*G15,"") | I15: 0 | J15: =IF(H15="","",H15+I15)
A16: 11 | E16: =IF(D16="H",5,IF(D16="M",3,IF(D16="L",1,""))) | G16: =IF(F16="H",5,IF(F16="M",3,IF(F16="L",1,""))) | H16: =IF(AND(E16<>"",G16<>""),E16*G16,"") | I16: 0 | J16: =IF(H16="","",H16+I16)
A17: 12 | E17: =IF(D17="H",5,IF(D17="M",3,IF(D17="L",1,""))) | G17: =IF(F17="H",5,IF(F17="M",3,IF(F17="L",1,""))) | H17: =IF(AND(E17<>"",G17<>""),E17*G17,"") | I17: 0 | J17: =IF(H17="","",H17+I17)
... A35: 30 | E35: =IF(D35="H",5,IF(D35="M",3,IF(D35="L",1,""))) | G35: =IF(F35="H",5,IF(F35="M",3,IF(F35="L",1,""))) | H35: =IF(AND(E35<>"",G35<>""),E35*G35,"") | I35: 0 | J35: =IF(H35="","",H35+I35)
J36: Total: | K36: =SUM(K6:K35) -> 0
A37: Adjust (+/-) lets you manually bump priority for individual items to break ties or override computed ranking. Est. Hours is optional.
